Numpy116ZhongwenWendang/README.md
Numpy116ZhongwenWendang/__init__.py
Numpy116ZhongwenWendang/__main__.py
Numpy116ZhongwenWendang/file.epub
Numpy116ZhongwenWendang/index.html
Numpy116ZhongwenWendang/css/__init__.py
Numpy116ZhongwenWendang/css/annotations.css
Numpy116ZhongwenWendang/css/main.css
Numpy116ZhongwenWendang/css/normalize.css
Numpy116ZhongwenWendang/css/popup.css
Numpy116ZhongwenWendang/font/__init__.py
Numpy116ZhongwenWendang/font/fontello.eot
Numpy116ZhongwenWendang/font/fontello.svg
Numpy116ZhongwenWendang/font/fontello.ttf
Numpy116ZhongwenWendang/font/fontello.woff
Numpy116ZhongwenWendang/img/__init__.py
Numpy116ZhongwenWendang/img/annotator-glyph-sprite.png
Numpy116ZhongwenWendang/img/annotator-icon-sprite.png
Numpy116ZhongwenWendang/img/apple-touch-icon.png
Numpy116ZhongwenWendang/img/cancelfullscreen.png
Numpy116ZhongwenWendang/img/close.png
Numpy116ZhongwenWendang/img/fullscreen.png
Numpy116ZhongwenWendang/img/loader.gif
Numpy116ZhongwenWendang/img/menu-icon.png
Numpy116ZhongwenWendang/img/save.png
Numpy116ZhongwenWendang/img/saved.png
Numpy116ZhongwenWendang/img/settings-s.png
Numpy116ZhongwenWendang/img/settings.png
Numpy116ZhongwenWendang/img/star.png
Numpy116ZhongwenWendang/js/__init__.py
Numpy116ZhongwenWendang/js/epub.js
Numpy116ZhongwenWendang/js/epub.min.js
Numpy116ZhongwenWendang/js/epub.min.map
Numpy116ZhongwenWendang/js/hooks.min.js
Numpy116ZhongwenWendang/js/hooks.min.map
Numpy116ZhongwenWendang/js/reader.js
Numpy116ZhongwenWendang/js/reader.js.map
Numpy116ZhongwenWendang/js/reader.min.js
Numpy116ZhongwenWendang/js/reader.min.map
Numpy116ZhongwenWendang/js/hooks/__init__.py
Numpy116ZhongwenWendang/js/hooks/extensions/__init__.py
Numpy116ZhongwenWendang/js/hooks/extensions/highlight.js
Numpy116ZhongwenWendang/js/libs/__init__.py
Numpy116ZhongwenWendang/js/libs/jquery.min.js
Numpy116ZhongwenWendang/js/libs/localforage.min.js
Numpy116ZhongwenWendang/js/libs/screenfull.js
Numpy116ZhongwenWendang/js/libs/screenfull.min.js
numpy_1_16_zhongwen_wendang-2024.3.5.0.dist-info/METADATA
numpy_1_16_zhongwen_wendang-2024.3.5.0.dist-info/WHEEL
numpy_1_16_zhongwen_wendang-2024.3.5.0.dist-info/entry_points.txt
numpy_1_16_zhongwen_wendang-2024.3.5.0.dist-info/top_level.txt
numpy_1_16_zhongwen_wendang-2024.3.5.0.dist-info/RECORD
